MANIFEST.in
README.md
requirements.txt
setup.py
collection/__init__.py
collection/admin.py
collection/context_processors.py
collection/models.py
collection/tests.py
collection/urls.py
collection/utils.py
collection/views.py
collection/migrations/0001_initial.py
collection/migrations/0002_auto__add_field_product_featured.py
collection/migrations/0003_auto__add_field_product_sold.py
collection/migrations/0004_auto__add_field_category_introduction_text.py
collection/migrations/0005_auto__add_field_product_live.py
collection/migrations/0006_auto__add_field_photo_product.py
collection/migrations/0007_auto__add_field_photo_sort_index.py
collection/migrations/0008_auto__del_field_photo_orientation.py
collection/migrations/0009_auto__chg_field_photo_image__chg_field_product_price_usd__chg_field_pr.py
collection/migrations/0010_auto__add_unique_product_slug.py
collection/migrations/0011_auto__add_field_product_reference.py
collection/migrations/0012_auto__add_field_product_company.py
collection/migrations/0013_auto__add_field_product_cost_purchase__add_field_product_cost_work__ch.py
collection/migrations/0014_auto__add_field_product_sold_date.py
collection/migrations/0015_auto__chg_field_product_price_gbp__chg_field_product_cost_purchase__ch.py
collection/migrations/0016_auto__chg_field_product_price_gbp__chg_field_product_cost_purchase__ch.py
collection/migrations/0017_auto__chg_field_product_price_gbp.py
collection/migrations/0018_auto__add_field_category_image.py
collection/migrations/__init__.py
links_collection.egg-info/PKG-INFO
links_collection.egg-info/SOURCES.txt
links_collection.egg-info/dependency_links.txt
links_collection.egg-info/requires.txt
links_collection.egg-info/top_level.txt