Metadata-Version: 1.0
Name: links-collection
Version: 0.1.9
Summary: Collection for Django
Home-page: http://www.linkscreative.co.uk/
Author: James Cleveland
Author-email: jamescleveland@gmail.com
License: LICENSE.txt
Platform: UNKNOWN
